acce/__init__.py
acce/__main__.py
acce/core.py
acce/installer.py
acce-1.0.1.dist-info/METADATA
acce-1.0.1.dist-info/WHEEL
acce-1.0.1.dist-info/entry_points.txt
acce-1.0.1.dist-info/top_level.txt
acce-1.0.1.dist-info/RECORD
